service_objects/__init__.py
service_objects/av3.py
service_objects/base.py
service_objects-0.1.0.dist-info/METADATA
service_objects-0.1.0.dist-info/WHEEL
service_objects-0.1.0.dist-info/licenses/LICENSE
service_objects-0.1.0.dist-info/RECORD
