Metadata-Version: 2.4
Name: service-objects
Version: 0.1.0
Summary: Python client for Service Objects APIs
Project-URL: Homepage, https://github.com/serviceobjects/service-objects
Author-email: Jan Rehorik <jrehorik@serviceobjects.com>
License: MIT
License-File: LICENSE
Requires-Python: >=3.9
Requires-Dist: httpx>=0.27
Requires-Dist: pydantic>=2.0
Requires-Dist: requests>=2.31
Provides-Extra: dev
Requires-Dist: pytest; extra == 'dev'
Requires-Dist: requests-mock; extra == 'dev'
